daily/__init__.py
daily/__init__.pyi
daily/daily.abi3.so
daily/py.typed
daily_python-0.23.0.dist-info/METADATA
daily_python-0.23.0.dist-info/WHEEL
daily_python-0.23.0.dist-info/RECORD
