Metadata-Version: 2.4
Name: daily-python
Version: 0.23.0
Classifier: Development Status :: 5 - Production/Stable
Classifier: Intended Audience :: Developers
Classifier: License :: OSI Approved :: BSD License
Classifier: Topic :: Communications :: Conferencing
Classifier: Topic :: Multimedia :: Sound/Audio
Classifier: Topic :: Multimedia :: Video
Classifier: Topic :: Scientific/Engineering :: Artificial Intelligence
Summary: Daily Client SDK for Python
Keywords: webrtc,audio,video,ai
License: BSD 2-Clause License
Requires-Python: >=3.7
Project-URL: Home, https://docs.daily.co/guides/products/ai-toolkit
Project-URL: Documentation, https://reference-python.daily.co
Project-URL: Source, https://github.com/daily-co/daily-python
Project-URL: Website, https://daily.co
